__init__.py
testspatialcdr.py
testspatialcdr-0.0.2.dist-info/LICENSE
testspatialcdr-0.0.2.dist-info/METADATA
testspatialcdr-0.0.2.dist-info/WHEEL
testspatialcdr-0.0.2.dist-info/top_level.txt
testspatialcdr-0.0.2.dist-info/RECORD
