Metadata-Version: 2.1
Name: testspatialcdr
Version: 0.0.2
Summary: Spacer package for Spatial Transcriptomics
Author-email: Ashish_Swain <swain.3@iitj.ac.in>
Maintainer-email: Shreshth Pal <shreshthpal@outlook.com>
License: Copyright (c) 2018 The Python Packaging Authority        
Project-URL: Homepage, https://github.com/swainasish/Spectacular
Project-URL: Bug Tracker, https://github.com/swainasish/Spectacular
Classifier: Programming Language :: Python :: 3
Classifier: License :: OSI Approved :: MIT License
Classifier: Operating System :: OS Independent
Requires-Python: >=3.8
License-File: LICENSE
Requires-Dist: pandas (>=1.3.5)
Requires-Dist: scikit-learn (==1.1.1)
Requires-Dist: numpy (>=1.17.3)
